opsys_motorized_stage/__init__.py
opsys_motorized_stage/nls4_controller.py
opsys_motorized_stage/smc_100_controller.py
opsys_motorized_stage/nsc_a1/PerformaxCom.dll
opsys_motorized_stage/nsc_a1/SiUSBXp.dll
opsys_motorized_stage/nsc_a1/__init__.py
opsys_motorized_stage/nsc_a1/nls4_linear_config.py
opsys_motorized_stage/nsc_a1/performax_interface.py
opsys_motorized_stage/smc_100/__init__.py
opsys_motorized_stage/smc_100/smc_100.py
opsys_motorized_stage-0.0.2.dist-info/LICENSE
opsys_motorized_stage-0.0.2.dist-info/METADATA
opsys_motorized_stage-0.0.2.dist-info/WHEEL
opsys_motorized_stage-0.0.2.dist-info/top_level.txt
opsys_motorized_stage-0.0.2.dist-info/RECORD
