Metadata-Version: 2.1
Name: opsys-motorized-stage
Version: 0.0.2
Summary: python package for motorized stage device control
Home-page: https://bitbucket.org/opsys_tech/opsys-motorized-stage/src/master/
Download-URL: https://bitbucket.org/opsys_tech/opsys-motorized-stage/src/master/
Author: dmitry.borovensky
Author-email: dmitry.borovensky@opsys-tech.com
License-File: LICENSE
